polygon_data_generator/__init__.py
polygon_data_generator/data_acquisition.py
polygon_data_generator-0.1.19.dist-info/METADATA
polygon_data_generator-0.1.19.dist-info/WHEEL
polygon_data_generator-0.1.19.dist-info/top_level.txt
polygon_data_generator-0.1.19.dist-info/RECORD
