Metadata-Version: 2.1
Name: polygon-data-generator
Version: 0.1.19
Summary: Demo library for polygon data
Home-page: https://medium-multiply.readthedocs.io/
Author: Trishita Singh
Author-email: ts4376@nyu.edu
License: MIT
Requires-Dist: datetime
Requires-Dist: polygon-api-client
Requires-Dist: sqlalchemy
